shapfs/__init__.py
shapfs/feature_selection.py
shapfs-0.0.1.dist-info/LICENSE
shapfs-0.0.1.dist-info/METADATA
shapfs-0.0.1.dist-info/WHEEL
shapfs-0.0.1.dist-info/top_level.txt
shapfs-0.0.1.dist-info/RECORD
